example/__init__.py
minicli/__init__.py
minicli-0.5.3.dist-info/METADATA
minicli-0.5.3.dist-info/WHEEL
minicli-0.5.3.dist-info/top_level.txt
minicli-0.5.3.dist-info/RECORD
