Metadata-Version: 2.1
Name: minicli
Version: 0.5.3
Summary: Minimalist CLI
Home-page: https://github.com/pyrates/minicli
Author: Pyrates
License: WTFPL
Keywords: cli command line interface
Classifier: Development Status :: 5 - Production/Stable
Classifier: Intended Audience :: Developers
Classifier: Operating System :: OS Independent
Classifier: Programming Language :: Python
Classifier: Programming Language :: Python :: 3.6
Classifier: Programming Language :: Python :: 3.7
Classifier: Programming Language :: Python :: 3.8
Classifier: Programming Language :: Python :: 3.9
Classifier: Programming Language :: Python :: 3.10
Provides-Extra: doc
Requires-Dist: mkdocs ==1.1.2 ; extra == 'doc'
Provides-Extra: test
Requires-Dist: pytest ==7.1.2 ; extra == 'test'
